{
  "blogs": [
    {
      "title": "abc",
      "content": "abc content",
      "id": "1"
    },
    {
      "id": "2",
      "title": "another title 2",
      "content": "some other content"
    },
    {
      "id": "3",
      "title": "another title 3",
      "content": "some other content"
    },
    {
      "id": "5",
      "title": "title 5",
      "content": "content 5"
    },
    {
      "id": "0d71",
      "title": "title 5",
      "content": "content 5"
    },
    {
      "id": "c726",
      "title": "Quas adipisci simili",
      "content": "Officia nostrum dele",
      "author": "admin",
      "created_at": "2025-08-08T01:59:07.571Z",
      "updated_at": "2025-08-08T01:59:07.571Z"
    },
    {
      "id": "f1c1",
      "title": "Porro et autem perfe",
      "content": "Quia id hic id eius ",
      "author": "admin",
      "created_at": "2025-08-08T02:00:50.920Z",
      "updated_at": "2025-08-08T02:00:50.920Z"
    },
    {
      "id": "3b59",
      "title": "Cupiditate odio exce",
      "content": "Sint vel porro mini",
      "author": "admin",
      "created_at": "2025-08-08T02:01:11.933Z",
      "updated_at": "2025-08-08T02:01:11.933Z"
    }
  ],
  "users": [
    {
      "id": "1",
      "name": "John Doe",
      "email": "john@doe.com",
      "password": "123456",
      "phone": "12344567"
    },
    {
      "id": "2",
      "name": "Jane Doe",
      "email": "jane@doe.com",
      "password": "123456",
      "phone": "12344567"
    },
    {
      "id": "3",
      "name": "Jim Doe",
      "email": "jim@doe.com",
      "password": "123456",
      "phone": "12344567"
    }
  ]
}